englishauction.py
mindpowered_englishauction/EnglishAuction.py
mindpowered_englishauction/__init__.py
mindpowered_englishauction-0.0.64.dist-info/LICENSE.txt
mindpowered_englishauction-0.0.64.dist-info/METADATA
mindpowered_englishauction-0.0.64.dist-info/WHEEL
mindpowered_englishauction-0.0.64.dist-info/top_level.txt
mindpowered_englishauction-0.0.64.dist-info/RECORD
