Metadata-Version: 2.1
Name: mindpowered-englishauction
Version: 0.0.64
Summary: Online auctions with ascending price and time limit
Home-page: https://mindpowered.dev/
Author: Mind Powered Corporation
Author-email: support@mindpowered.dev
License: MIT
Platform: UNKNOWN
Classifier: Programming Language :: Python :: 3
Classifier: Operating System :: OS Independent
Classifier: License :: OSI Approved :: MIT License
Requires-Dist: mindpowered-maglev
